taskiq_elastic_apm/__init__.py
taskiq_elastic_apm/middleware.py
taskiq_elastic_apm-0.0.4.dist-info/METADATA
taskiq_elastic_apm-0.0.4.dist-info/WHEEL
taskiq_elastic_apm-0.0.4.dist-info/top_level.txt
taskiq_elastic_apm-0.0.4.dist-info/RECORD
