Metadata-Version: 2.1
Name: taskiq-elastic-apm
Version: 0.0.4
Summary: A middleware for TaskIQ with Elastic APM integration
Home-page: https://github.com/h0rn3t/taskiq-elastic-apm
Author: Eugene Shershen
Author-email: h0rn3t.null@gmail.com
License: MIT
Classifier: Development Status :: 3 - Alpha
Classifier: Intended Audience :: Developers
Classifier: License :: OSI Approved :: MIT License
Classifier: Programming Language :: Python :: 3
Classifier: Programming Language :: Python :: 3.8
Classifier: Programming Language :: Python :: 3.9
Classifier: Programming Language :: Python :: 3.10
Classifier: Programming Language :: Python :: 3.11
Classifier: Programming Language :: Python :: 3.12
Classifier: Operating System :: OS Independent
Requires-Python: >=3.8
Requires-Dist: taskiq >=0.10.4
Requires-Dist: elastic-apm >=6.20.0
